[
{"id": "8-0", "title": "Area Outage", "desc": {"n_out": 1, "cust_a": {"val": 4, "mask": 5}, "inc_id": null, "crew_status": null, "cluster": false, "etr": "2023-10-25T15:30:00Z", "etr_confidence": null, "comments": null, "cause": {"EN-US": "Pending crew assessment", "orig": "NOCAUSE"}, "crew_icon": false, "start_time": "2023-10-24T14:47:56Z", "lastFileUpdate": "2023-10-24T15:50:07.591Z"}, "geom": {"p": ["u|qgGl|w}N"]}, "source": "https://kubra.io/cluster-data/203/227de1f9-4adc-4fc9-98cb-dc2b847c0549/f94a9001-559d-46b5-9d94-e69fbdc030ee/public/cluster-1/03022302.json"},
{"id": "8-1", "title": "Area Outage", "desc": {"n_out": 1, "cust_a": {"val": 4, "mask": 5}, "inc_id": null, "crew_status": null, "cluster": false, "etr": "2023-10-25T13:30:00Z", "etr_confidence": null, "comments": null, "cause": {"EN-US": "Pending crew assessment", "orig": "NOCAUSE"}, "crew_icon": false, "start_time": "2023-10-23T18:57:07Z", "lastFileUpdate": "2023-10-24T15:50:07.591Z"}, "geom": {"p": ["aaugGxil{N"]}, "source": "https://kubra.io/cluster-data/203/227de1f9-4adc-4fc9-98cb-dc2b847c0549/f94a9001-559d-46b5-9d94-e69fbdc030ee/public/cluster-1/03022302.json"},
{"id": "8-2", "title": "Area Outage", "desc": {"n_out": 1, "cust_a": {"val": 4, "mask": 5}, "inc_id": null, "crew_status": null, "cluster": false, "etr": "2023-10-25T14:45:00Z", "etr_confidence": null, "comments": null, "cause": {"EN-US": "Pending crew assessment", "orig": "NOCAUSE"}, "crew_icon": false, "start_time": "2023-10-24T14:00:43Z", "lastFileUpdate": "2023-10-24T15:50:07.591Z"}, "geom": {"p": ["mlgfGdgz{N"]}, "source": "https://kubra.io/cluster-data/203/227de1f9-4adc-4fc9-98cb-dc2b847c0549/f94a9001-559d-46b5-9d94-e69fbdc030ee/public/cluster-1/03022302.json"},
{"id": "8-3", "title": "Area Outage", "desc": {"n_out": 1, "cust_a": {"val": 4, "mask": 5}, "inc_id": null, "crew_status": null, "cluster": false, "etr": "2023-10-25T12:15:00Z", "etr_confidence": null, "comments": null, "cause": {"EN-US": "Pending crew assessment", "orig": "NOCAUSE"}, "crew_icon": false, "start_time": "2023-10-24T11:43:25Z", "lastFileUpdate": "2023-10-24T15:50:07.591Z"}, "geom": {"p": ["{vniGjc~yN"]}, "source": "https://kubra.io/cluster-data/203/227de1f9-4adc-4fc9-98cb-dc2b847c0549/f94a9001-559d-46b5-9d94-e69fbdc030ee/public/cluster-1/03022302.json"},
{"id": "8-0", "title": "Area Outage", "desc": {"n_out": 1, "cust_a": {"val": 4, "mask": 5}, "inc_id": null, "crew_status": null, "cluster": false, "etr": "2023-10-25T14:15:00Z", "etr_confidence": null, "comments": null, "cause": {"EN-US": "Pending crew assessment", "orig": "NOCAUSE"}, "crew_icon": false, "start_time": "2023-10-24T13:36:59Z", "lastFileUpdate": "2023-10-24T15:50:07.591Z"}, "geom": {"p": ["qyngG~phxN"]}, "source": "https://kubra.io/cluster-data/303/227de1f9-4adc-4fc9-98cb-dc2b847c0549/f94a9001-559d-46b5-9d94-e69fbdc030ee/public/cluster-1/03022303.json"},
{"id": "9-0", "title": "Area Outage", "desc": {"n_out": 1, "cust_a": {"val": 4, "mask": 5}, "inc_id": null, "crew_status": null, "cluster": false, "etr": "2023-10-25T15:45:00Z", "etr_confidence": null, "comments": null, "cause": {"EN-US": "Reqd to repair/upgrade equip", "orig": "PLANNED INTENTIONAL"}, "crew_icon": false, "start_time": "2023-10-24T15:13:23.195Z", "lastFileUpdate": "2023-10-24T15:50:07.591Z"}, "geom": {"p": ["gcjcGxpb`O"]}, "source": "https://kubra.io/cluster-data/002/227de1f9-4adc-4fc9-98cb-dc2b847c0549/f94a9001-559d-46b5-9d94-e69fbdc030ee/public/cluster-1/030223200.json"},
{"id": "10-0", "title": "Area Outage", "desc": {"n_out": 1, "cust_a": {"val": 4, "mask": 5}, "inc_id": null, "crew_status": null, "cluster": false, "etr": "2023-10-24T18:30:00Z", "etr_confidence": null, "comments": null, "cause": {"EN-US": "Equipment problem", "orig": "EQUIPMENT FAILURE"}, "crew_icon": false, "start_time": "2023-10-24T12:58:51Z", "lastFileUpdate": "2023-10-24T15:50:07.591Z"}, "geom": {"p": ["_pidGvloyN"]}, "source": "https://kubra.io/cluster-data/110/227de1f9-4adc-4fc9-98cb-dc2b847c0549/f94a9001-559d-46b5-9d94-e69fbdc030ee/public/cluster-1/0302232011.json"},
{"id": "11-0", "title": "Area Outage", "desc": {"n_out": 1, "cust_a": {"val": 4, "mask": 5}, "inc_id": null, "crew_status": null, "cluster": false, "etr": "2023-10-24T19:45:00Z", "etr_confidence": null, "comments": null, "cause": {"EN-US": "Pending crew assessment", "orig": "NOCAUSE"}, "crew_icon": false, "start_time": "2023-10-24T12:58:19Z", "lastFileUpdate": "2023-10-24T15:50:07.591Z"}, "geom": {"a": ["wvtcGzer{Nu@vAgB\\|CuB"], "p": ["}xtcG~gr{N"]}, "source": "https://kubra.io/cluster-data/121/227de1f9-4adc-4fc9-98cb-dc2b847c0549/f94a9001-559d-46b5-9d94-e69fbdc030ee/public/cluster-1/03022320121.json"},
{"id": "12-0", "title": "Area Outage", "desc": {"n_out": 1, "cust_a": {"val": 4, "mask": 5}, "inc_id": null, "crew_status": null, "cluster": false, "etr": "2023-10-24T16:30:00Z", "etr_confidence": null, "comments": null, "cause": {"EN-US": "Equipment problem", "orig": "EQUIPMENT FAILURE"}, "crew_icon": false, "start_time": "2023-10-23T21:23:33Z", "lastFileUpdate": "2023-10-24T15:50:07.591Z"}, "geom": {"p": ["ysicG~_m}N"]}, "source": "https://kubra.io/cluster-data/022/227de1f9-4adc-4fc9-98cb-dc2b847c0549/f94a9001-559d-46b5-9d94-e69fbdc030ee/public/cluster-1/030223201220.json"},
{"id": "12-0", "title": "Area Outage", "desc": {"n_out": 1, "cust_a": {"val": 4, "mask": 5}, "inc_id": null, "crew_status": null, "cluster": false, "etr": "2023-10-25T13:15:00Z", "etr_confidence": null, "comments": null, "cause": {"EN-US": "Equipment problem", "orig": "EQUIPMENT FAILURE"}, "crew_icon": false, "start_time": "2023-10-24T12:34:35Z", "lastFileUpdate": "2023-10-24T15:50:07.591Z"}, "geom": {"p": ["agncGrtv|N"]}, "source": "https://kubra.io/cluster-data/122/227de1f9-4adc-4fc9-98cb-dc2b847c0549/f94a9001-559d-46b5-9d94-e69fbdc030ee/public/cluster-1/030223201221.json"},
{"id": "14-0", "title": "Area Outage", "desc": {"n_out": 2, "cust_a": {"val": 7}, "inc_id": null, "crew_status": null, "cluster": true, "etr": "2023-10-25T13:45:00Z", "etr_confidence": null, "outages": [{"cust_a": {"val": 6}, "crew_icon": false, "etr": "2023-10-24T20:00:00Z", "cause": {"EN-US": "Equipment problem", "orig": "EQUIPMENT FAILURE"}, "start_time": "2023-10-24T12:56:03Z", "lastFileUpdate": "2023-10-24T15:50:07.591Z"}, {"cust_a": {"val": 4, "mask": 5}, "crew_icon": false, "etr": "2023-10-25T13:45:00Z", "cause": {"EN-US": "Pending crew assessment", "orig": "NOCAUSE"}, "start_time": "2023-10-24T12:56:03Z", "lastFileUpdate": "2023-10-24T15:50:07.591Z"}], "comments": null, "cause": null, "crew_icon": false, "start_time": "2023-10-24T12:56:03Z"}, "geom": {"p": ["ga_cGrea}N"]}, "source": "https://kubra.io/cluster-data/203/227de1f9-4adc-4fc9-98cb-dc2b847c0549/f94a9001-559d-46b5-9d94-e69fbdc030ee/public/cluster-1/03022320122302.json"},
{"id": "12-0", "title": "Area Outage", "desc": {"n_out": 1, "cust_a": {"val": 4, "mask": 5}, "inc_id": null, "crew_status": null, "cluster": false, "etr": "2023-10-25T04:45:00Z", "etr_confidence": null, "comments": null, "cause": {"EN-US": "Pending crew assessment", "orig": "NOCAUSE"}, "crew_icon": false, "start_time": "2023-10-23T14:57:52Z", "lastFileUpdate": "2023-10-24T15:50:07.591Z"}, "geom": {"p": ["ebmcGhcn|N"]}, "source": "https://kubra.io/cluster-data/032/227de1f9-4adc-4fc9-98cb-dc2b847c0549/f94a9001-559d-46b5-9d94-e69fbdc030ee/public/cluster-1/030223201230.json"},
{"id": "13-0", "title": "Area Outage", "desc": {"n_out": 1, "cust_a": {"val": 4, "mask": 5}, "inc_id": null, "crew_status": null, "cluster": false, "etr": "2023-10-24T17:30:00Z", "etr_confidence": null, "comments": null, "cause": {"EN-US": "Equipment problem", "orig": "EQUIPMENT FAILURE"}, "crew_icon": false, "start_time": "2023-10-23T16:48:28Z", "lastFileUpdate": "2023-10-24T15:50:07.591Z"}, "geom": {"p": ["mplcGdhu{N"]}, "source": "https://kubra.io/cluster-data/113/227de1f9-4adc-4fc9-98cb-dc2b847c0549/f94a9001-559d-46b5-9d94-e69fbdc030ee/public/cluster-1/0302232012311.json"},
{"id": "14-0", "title": "Area Outage", "desc": {"n_out": 2, "cust_a": {"val": 8}, "inc_id": null, "crew_status": null, "cluster": true, "etr": "2023-10-24T21:30:00Z", "etr_confidence": null, "outages": [{"cust_a": {"val": 6}, "crew_icon": false, "etr": "2023-10-24T21:00:00Z", "cause": {"EN-US": "Animal/bird damaged DTE equip", "orig": "ANIMAL"}, "start_time": "2023-10-24T14:09:58Z", "lastFileUpdate": "2023-10-24T15:50:07.591Z"}, {"cust_a": {"val": 4, "mask": 5}, "crew_icon": false, "etr": "2023-10-24T21:30:00Z", "cause": {"EN-US": "Animal/bird damaged DTE equip", "orig": "ANIMAL"}, "start_time": "2023-10-24T14:36:28Z", "lastFileUpdate": "2023-10-24T15:50:07.591Z"}], "comments": null, "cause": null, "crew_icon": false, "start_time": "2023-10-24T14:09:58Z"}, "geom": {"p": ["y~ccGhj|{N"]}, "source": "https://kubra.io/cluster-data/321/227de1f9-4adc-4fc9-98cb-dc2b847c0549/f94a9001-559d-46b5-9d94-e69fbdc030ee/public/cluster-1/03022320123123.json"},
{"id": "13-0", "title": "Area Outage", "desc": {"n_out": 1, "cust_a": {"val": 4, "mask": 5}, "inc_id": null, "crew_status": null, "cluster": false, "etr": "2023-10-25T15:00:00Z", "etr_confidence": null, "comments": null, "cause": {"EN-US": "Reqd to repair/upgrade equip", "orig": "PLANNED INTENTIONAL"}, "crew_icon": false, "start_time": "2023-10-24T14:21:46.116Z", "lastFileUpdate": "2023-10-24T15:50:07.591Z"}, "geom": {"p": ["ws~bGz`a|N"]}, "source": "https://kubra.io/cluster-data/033/227de1f9-4adc-4fc9-98cb-dc2b847c0549/f94a9001-559d-46b5-9d94-e69fbdc030ee/public/cluster-1/0302232012330.json"},
{"id": "14-0", "title": "Area Outage", "desc": {"n_out": 2, "cust_a": {"val": 4, "mask": 5}, "inc_id": null, "crew_status": null, "cluster": true, "etr": "2023-10-25T14:30:00Z", "etr_confidence": null, "outages": [{"cust_a": {"val": 4, "mask": 5}, "crew_icon": false, "etr": "2023-10-25T14:30:00Z", "cause": {"EN-US": "Pending crew assessment", "orig": "NOCAUSE"}, "start_time": "2023-10-24T13:47:35Z", "lastFileUpdate": "2023-10-24T15:50:07.591Z"}, {"cust_a": {"val": 4, "mask": 5}, "crew_icon": false, "etr": "2023-10-25T14:30:00Z", "cause": {"EN-US": "Pending crew assessment", "orig": "NOCAUSE"}, "start_time": "2023-10-24T13:45:34Z", "lastFileUpdate": "2023-10-24T15:50:07.591Z"}], "comments": null, "cause": null, "crew_icon": false, "start_time": "2023-10-24T13:45:34Z"}, "geom": {"p": ["ayvbGjn{{N"]}, "source": "https://kubra.io/cluster-data/323/227de1f9-4adc-4fc9-98cb-dc2b847c0549/f94a9001-559d-46b5-9d94-e69fbdc030ee/public/cluster-1/03022320123323.json"},
{"id": "11-0", "title": "Area Outage", "desc": {"n_out": 1, "cust_a": {"val": 4, "mask": 5}, "inc_id": null, "crew_status": null, "cluster": false, "etr": "2023-10-24T17:30:00Z", "etr_confidence": null, "comments": null, "cause": {"EN-US": "Pending crew assessment", "orig": "NOCAUSE"}, "crew_icon": false, "start_time": "2023-10-23T06:39:42Z", "lastFileUpdate": "2023-10-24T15:50:07.591Z"}, "geom": {"p": ["uc|cGthm{N"]}, "source": "https://kubra.io/cluster-data/031/227de1f9-4adc-4fc9-98cb-dc2b847c0549/f94a9001-559d-46b5-9d94-e69fbdc030ee/public/cluster-1/03022320130.json"},
{"id": "11-0", "title": "Area Outage", "desc": {"n_out": 1, "cust_a": {"val": 4, "mask": 5}, "inc_id": null, "crew_status": null, "cluster": false, "etr": "2023-10-25T14:15:00Z", "etr_confidence": null, "comments": null, "cause": {"EN-US": "Reqd to repair/upgrade equip", "orig": "PLANNED INTENTIONAL"}, "crew_icon": false, "start_time": "2023-10-24T13:42:23.245Z", "lastFileUpdate": "2023-10-24T15:50:07.591Z"}, "geom": {"p": ["ok_cGzre{N"]}, "source": "https://kubra.io/cluster-data/231/227de1f9-4adc-4fc9-98cb-dc2b847c0549/f94a9001-559d-46b5-9d94-e69fbdc030ee/public/cluster-1/03022320132.json"},
{"id": "11-1", "title": "Area Outage", "desc": {"n_out": 1, "cust_a": {"val": 4, "mask": 5}, "inc_id": null, "crew_status": null, "cluster": false, "etr": "2023-10-25T12:30:00Z", "etr_confidence": null, "comments": null, "cause": {"EN-US": "Equipment problem", "orig": "EQUIPMENT FAILURE"}, "crew_icon": false, "start_time": "2023-10-23T19:58:38Z", "lastFileUpdate": "2023-10-24T15:50:07.591Z"}, "geom": {"p": ["eeicGtjxzN"]}, "source": "https://kubra.io/cluster-data/231/227de1f9-4adc-4fc9-98cb-dc2b847c0549/f94a9001-559d-46b5-9d94-e69fbdc030ee/public/cluster-1/03022320132.json"},
{"id": "11-2", "title": "Area Outage", "desc": {"n_out": 1, "cust_a": {"val": 4, "mask": 5}, "inc_id": null, "crew_status": null, "cluster": false, "etr": "2023-10-24T19:30:00Z", "etr_confidence": null, "comments": null, "cause": {"EN-US": "No problem upon crew arrival", "orig": "NO ISSUES FOUND"}, "crew_icon": false, "start_time": "2023-10-24T12:46:08Z", "lastFileUpdate": "2023-10-24T15:50:07.591Z"}, "geom": {"a": ["cuhcGj}g{NsBvCyEk@lIkB"], "p": ["yyhcG``h{N"]}, "source": "https://kubra.io/cluster-data/231/227de1f9-4adc-4fc9-98cb-dc2b847c0549/f94a9001-559d-46b5-9d94-e69fbdc030ee/public/cluster-1/03022320132.json"},
{"id": "11-3", "title": "Area Outage", "desc": {"n_out": 1, "cust_a": {"val": 4, "mask": 5}, "inc_id": null, "crew_status": null, "cluster": false, "etr": "2023-10-25T13:30:00Z", "etr_confidence": null, "comments": null, "cause": {"EN-US": "Pending crew assessment", "orig": "NOCAUSE"}, "crew_icon": false, "start_time": "2023-10-24T12:58:24Z", "lastFileUpdate": "2023-10-24T15:50:07.591Z"}, "geom": {"p": ["aamcGlra{N"]}, "source": "https://kubra.io/cluster-data/231/227de1f9-4adc-4fc9-98cb-dc2b847c0549/f94a9001-559d-46b5-9d94-e69fbdc030ee/public/cluster-1/03022320132.json"},
{"id": "11-4", "title": "Area Outage", "desc": {"n_out": 1, "cust_a": {"val": 9}, "inc_id": null, "crew_status": null, "cluster": false, "etr": "2023-10-24T20:30:00Z", "etr_confidence": null, "comments": null, "cause": {"EN-US": "Reqd to repair/upgrade equip", "orig": "PLANNED INTENTIONAL"}, "crew_icon": false, "start_time": "2023-10-24T13:35:36Z", "lastFileUpdate": "2023-10-24T15:50:07.591Z"}, "geom": {"a": ["yalcGtlo{Nw@nHuAj@JiB`CqF"], "p": ["cdlcGfso{N"]}, "source": "https://kubra.io/cluster-data/231/227de1f9-4adc-4fc9-98cb-dc2b847c0549/f94a9001-559d-46b5-9d94-e69fbdc030ee/public/cluster-1/03022320132.json"},
{"id": "14-0", "title": "Area Outage", "desc": {"n_out": 2, "cust_a": {"val": 4, "mask": 5}, "inc_id": null, "crew_status": null, "cluster": true, "etr": "2023-10-25T13:45:00Z", "etr_confidence": null, "outages": [{"cust_a": {"val": 4, "mask": 5}, "crew_icon": false, "etr": "2023-10-25T13:45:00Z", "cause": {"EN-US": "Pending crew assessment", "orig": "NOCAUSE"}, "start_time": "2023-10-24T13:03:41Z", "lastFileUpdate": "2023-10-24T15:50:07.591Z"}, {"cust_a": {"val": 4, "mask": 5}, "crew_icon": false, "etr": "2023-10-25T02:00:00Z", "cause": {"EN-US": "Pending crew assessment", "orig": "NOCAUSE"}, "start_time": "2023-10-23T21:04:46Z", "lastFileUpdate": "2023-10-24T15:50:07.591Z"}], "comments": null, "cause": null, "crew_icon": false, "start_time": "2023-10-23T21:04:46Z"}, "geom": {"p": ["qnxbGt~jzN"]}, "source": "https://kubra.io/cluster-data/222/227de1f9-4adc-4fc9-98cb-dc2b847c0549/f94a9001-559d-46b5-9d94-e69fbdc030ee/public/cluster-1/03022320133222.json"},
{"id": "9-0", "title": "Area Outage", "desc": {"n_out": 1, "cust_a": {"val": 4, "mask": 5}, "inc_id": null, "crew_status": null, "cluster": false, "etr": "2023-10-25T14:45:00Z", "etr_confidence": null, "comments": null, "cause": {"EN-US": "Pending crew assessment", "orig": "NOCAUSE"}, "crew_icon": false, "start_time": "2023-10-24T14:08:17Z", "lastFileUpdate": "2023-10-24T15:50:07.591Z"}, "geom": {"p": ["_o{`G|c`~N"]}, "source": "https://kubra.io/cluster-data/202/227de1f9-4adc-4fc9-98cb-dc2b847c0549/f94a9001-559d-46b5-9d94-e69fbdc030ee/public/cluster-1/030223202.json"},
{"id": "11-0", "title": "Area Outage", "desc": {"n_out": 1, "cust_a": {"val": 4, "mask": 5}, "inc_id": null, "crew_status": null, "cluster": false, "etr": "2023-10-25T03:00:00Z", "etr_confidence": null, "comments": null, "cause": {"EN-US": "No problem upon crew arrival", "orig": "NO ISSUES FOUND"}, "crew_icon": false, "start_time": "2023-10-23T21:58:55Z", "lastFileUpdate": "2023-10-24T15:50:07.591Z"}, "geom": {"p": ["ioubGzf{|N"]}, "source": "https://kubra.io/cluster-data/003/227de1f9-4adc-4fc9-98cb-dc2b847c0549/f94a9001-559d-46b5-9d94-e69fbdc030ee/public/cluster-1/03022320300.json"},
{"id": "11-1", "title": "Area Outage", "desc": {"n_out": 1, "cust_a": {"val": 4, "mask": 5}, "inc_id": null, "crew_status": null, "cluster": false, "etr": "2023-10-25T13:45:00Z", "etr_confidence": null, "comments": null, "cause": {"EN-US": "Equipment problem", "orig": "EQUIPMENT FAILURE"}, "crew_icon": false, "start_time": "2023-10-24T13:01:53.179Z", "lastFileUpdate": "2023-10-24T15:50:07.591Z"}, "geom": {"p": ["sxfbGrbr}N"]}, "source": "https://kubra.io/cluster-data/003/227de1f9-4adc-4fc9-98cb-dc2b847c0549/f94a9001-559d-46b5-9d94-e69fbdc030ee/public/cluster-1/03022320300.json"},
{"id": "12-0", "title": "Area Outage", "desc": {"n_out": 1, "cust_a": {"val": 4, "mask": 5}, "inc_id": null, "crew_status": null, "cluster": false, "etr": "2023-10-25T03:00:00Z", "etr_confidence": null, "comments": null, "cause": {"EN-US": "Pending crew assessment", "orig": "NOCAUSE"}, "crew_icon": false, "start_time": "2023-10-23T21:58:08Z", "lastFileUpdate": "2023-10-24T15:50:07.591Z"}, "geom": {"p": ["}wqbGjjd|N"]}, "source": "https://kubra.io/cluster-data/010/227de1f9-4adc-4fc9-98cb-dc2b847c0549/f94a9001-559d-46b5-9d94-e69fbdc030ee/public/cluster-1/030223203010.json"},
{"id": "12-0", "title": "Area Outage", "desc": {"n_out": 1, "cust_a": {"val": 4, "mask": 5}, "inc_id": null, "crew_status": null, "cluster": false, "etr": "2023-10-25T03:00:00Z", "etr_confidence": null, "comments": null, "cause": {"EN-US": "Pending crew assessment", "orig": "NOCAUSE"}, "crew_icon": false, "start_time": "2023-10-23T16:13:56Z", "lastFileUpdate": "2023-10-24T15:50:07.591Z"}, "geom": {"p": ["ckubGjkx{N"]}, "source": "https://kubra.io/cluster-data/110/227de1f9-4adc-4fc9-98cb-dc2b847c0549/f94a9001-559d-46b5-9d94-e69fbdc030ee/public/cluster-1/030223203011.json"},
{"id": "14-0", "title": "Area Outage", "desc": {"n_out": 2, "cust_a": {"val": 18}, "inc_id": null, "crew_status": null, "cluster": true, "etr": "2023-10-24T22:00:00Z", "etr_confidence": null, "outages": [{"cust_a": {"val": 17}, "crew_icon": false, "etr": "2023-10-24T22:00:00Z", "cause": {"EN-US": "Reqd to repair/upgrade equip", "orig": "PLANNED INTENTIONAL"}, "start_time": "2023-10-24T15:14:03.496Z", "lastFileUpdate": "2023-10-24T15:50:07.591Z"}, {"cust_a": {"val": 4, "mask": 5}, "crew_icon": false, "etr": "ETR-NULL", "comments": "Power problem is being assessed. A restoration estimate is in progress.", "cause": {"EN-US": "Pending crew assessment", "orig": "NOCAUSE"}, "start_time": "2023-10-24T15:24Z", "lastFileUpdate": "2023-10-24T15:50:07.591Z"}], "comments": null, "cause": null, "crew_icon": false, "start_time": "2023-10-24T15:14:03.496Z"}, "geom": {"p": ["_z_bGddp|N"]}, "source": "https://kubra.io/cluster-data/222/227de1f9-4adc-4fc9-98cb-dc2b847c0549/f94a9001-559d-46b5-9d94-e69fbdc030ee/public/cluster-1/03022320301222.json"},
{"id": "12-0", "title": "Area Outage", "desc": {"n_out": 1, "cust_a": {"val": 4, "mask": 5}, "inc_id": null, "crew_status": null, "cluster": false, "etr": "2023-10-25T14:30:00Z", "etr_confidence": null, "comments": null, "cause": {"EN-US": "Pending crew assessment", "orig": "NOCAUSE"}, "crew_icon": false, "start_time": "2023-10-23T11:07:46Z", "lastFileUpdate": "2023-10-24T15:50:07.591Z"}, "geom": {"p": ["qeibGz{u{N"]}, "source": "https://kubra.io/cluster-data/310/227de1f9-4adc-4fc9-98cb-dc2b847c0549/f94a9001-559d-46b5-9d94-e69fbdc030ee/public/cluster-1/030223203013.json"},
{"id": "12-0", "title": "Area Outage", "desc": {"n_out": 1, "cust_a": {"val": 10}, "inc_id": null, "crew_status": null, "cluster": false, "etr": "2023-10-24T21:15:00Z", "etr_confidence": null, "comments": null, "cause": {"EN-US": "Reqd to repair/upgrade equip", "orig": "PLANNED INTENTIONAL"}, "crew_icon": false, "start_time": "2023-10-24T14:23:02.622Z", "lastFileUpdate": "2023-10-24T15:50:07.591Z"}, "geom": {"a": ["mbvaGbbr{NyDe@Gu@?m@|@i@^G`BF@rD"], "p": ["eevaG`_r{N"]}, "source": "https://kubra.io/cluster-data/130/227de1f9-4adc-4fc9-98cb-dc2b847c0549/f94a9001-559d-46b5-9d94-e69fbdc030ee/public/cluster-1/030223203031.json"},
{"id": "12-1", "title": "Area Outage", "desc": {"n_out": 1, "cust_a": {"val": 4, "mask": 5}, "inc_id": null, "crew_status": null, "cluster": false, "etr": "2023-10-24T19:45:00Z", "etr_confidence": null, "comments": null, "cause": {"EN-US": "No problem upon crew arrival", "orig": "NO ISSUES FOUND"}, "crew_icon": false, "start_time": "2023-10-21T04:57:35Z", "lastFileUpdate": "2023-10-24T15:50:07.591Z"}, "geom": {"p": ["wotaGhay{N"]}, "source": "https://kubra.io/cluster-data/130/227de1f9-4adc-4fc9-98cb-dc2b847c0549/f94a9001-559d-46b5-9d94-e69fbdc030ee/public/cluster-1/030223203031.json"},
{"id": "12-2", "title": "Area Outage", "desc": {"n_out": 1, "cust_a": {"val": 4, "mask": 5}, "inc_id": null, "crew_status": null, "cluster": false, "etr": "2023-10-24T21:30:00Z", "etr_confidence": null, "comments": null, "cause": {"EN-US": "Pending crew assessment", "orig": "NOCAUSE"}, "crew_icon": false, "start_time": "2023-10-24T14:45:59.282Z", "lastFileUpdate": "2023-10-24T15:50:07.591Z"}, "geom": {"p": ["yfzaGpx_|N"]}, "source": "https://kubra.io/cluster-data/130/227de1f9-4adc-4fc9-98cb-dc2b847c0549/f94a9001-559d-46b5-9d94-e69fbdc030ee/public/cluster-1/030223203031.json"},
{"id": "14-0", "title": "Area Outage", "desc": {"n_out": 4, "cust_a": {"val": 19}, "inc_id": null, "crew_status": null, "cluster": true, "etr": "2023-10-24T22:15:00Z", "etr_confidence": null, "outages": [{"cust_a": {"val": 4, "mask": 5}, "crew_icon": false, "etr": "2023-10-24T22:15:00Z", "cause": {"EN-US": "Pending crew assessment", "orig": "NOCAUSE"}, "start_time": "2023-10-24T15:23:19Z", "lastFileUpdate": "2023-10-24T15:50:07.591Z"}, {"cust_a": {"val": 5}, "crew_icon": false, "etr": "2023-10-24T22:15:00Z", "cause": {"EN-US": "Pending crew assessment", "orig": "NOCAUSE"}, "start_time": "2023-10-24T15:23:23Z", "lastFileUpdate": "2023-10-24T15:50:07.591Z"}, {"cust_a": {"val": 4, "mask": 5}, "crew_icon": false, "etr": "ETR-NULL", "comments": "Power problem is being assessed. A restoration estimate is in progress.", "cause": {"EN-US": "Pending crew assessment", "orig": "NOCAUSE"}, "start_time": "2023-10-24T15:29:44Z", "lastFileUpdate": "2023-10-24T15:50:07.591Z"}, {"cust_a": {"val": 10}, "crew_icon": false, "etr": "2023-10-24T22:15:00Z", "cause": {"EN-US": "Pending crew assessment", "orig": "NOCAUSE"}, "start_time": "2023-10-24T15:23:19Z", "lastFileUpdate": "2023-10-24T15:50:07.591Z"}], "comments": null, "cause": null, "crew_icon": false, "start_time": "2023-10-24T15:23:19Z"}, "geom": {"p": ["_ymaGdc~{N"]}, "source": "https://kubra.io/cluster-data/003/227de1f9-4adc-4fc9-98cb-dc2b847c0549/f94a9001-559d-46b5-9d94-e69fbdc030ee/public/cluster-1/03022320303300.json"},
{"id": "14-1", "title": "Area Outage", "desc": {"n_out": 1, "cust_a": {"val": 4, "mask": 5}, "inc_id": null, "crew_status": null, "cluster": false, "etr": "2023-10-25T02:15:00Z", "etr_confidence": null, "comments": null, "cause": {"EN-US": "No problem upon crew arrival", "orig": "NO ISSUES FOUND"}, "crew_icon": false, "start_time": "2023-10-23T21:21:18Z", "lastFileUpdate": "2023-10-24T15:50:07.591Z"}, "geom": {"p": ["mcnaGno}{N"]}, "source": "https://kubra.io/cluster-data/003/227de1f9-4adc-4fc9-98cb-dc2b847c0549/f94a9001-559d-46b5-9d94-e69fbdc030ee/public/cluster-1/03022320303300.json"},
{"id": "13-0", "title": "Area Outage", "desc": {"n_out": 1, "cust_a": {"val": 4, "mask": 5}, "inc_id": null, "crew_status": null, "cluster": false, "etr": "2023-10-25T03:30:00Z", "etr_confidence": null, "comments": null, "cause": {"EN-US": "Pending crew assessment", "orig": "NOCAUSE"}, "crew_icon": false, "start_time": "2023-10-23T15:49:28Z", "lastFileUpdate": "2023-10-24T15:50:07.591Z"}, "geom": {"p": ["}|jaG`~q{N"]}, "source": "https://kubra.io/cluster-data/133/227de1f9-4adc-4fc9-98cb-dc2b847c0549/f94a9001-559d-46b5-9d94-e69fbdc030ee/public/cluster-1/0302232030331.json"},
{"id": "12-0", "title": "Area Outage", "desc": {"n_out": 1, "cust_a": {"val": 4, "mask": 5}, "inc_id": null, "crew_status": null, "cluster": false, "etr": "2023-10-25T14:45:00Z", "etr_confidence": null, "comments": null, "cause": {"EN-US": "Reqd to repair/upgrade equip", "orig": "PLANNED INTENTIONAL"}, "crew_icon": false, "start_time": "2023-10-24T14:00:00.447Z", "lastFileUpdate": "2023-10-24T15:50:07.591Z"}, "geom": {"p": ["qhtbGbba{N"]}, "source": "https://kubra.io/cluster-data/001/227de1f9-4adc-4fc9-98cb-dc2b847c0549/f94a9001-559d-46b5-9d94-e69fbdc030ee/public/cluster-1/030223203100.json"},
{"id": "12-1", "title": "Area Outage", "desc": {"n_out": 1, "cust_a": {"val": 4, "mask": 5}, "inc_id": null, "crew_status": null, "cluster": false, "etr": "2023-10-25T14:30:00Z", "etr_confidence": null, "comments": null, "cause": {"EN-US": "Pending crew assessment", "orig": "NOCAUSE"}, "crew_icon": false, "start_time": "2023-10-24T13:47:31Z", "lastFileUpdate": "2023-10-24T15:50:07.591Z"}, "geom": {"p": ["qribG`pj{N"]}, "source": "https://kubra.io/cluster-data/001/227de1f9-4adc-4fc9-98cb-dc2b847c0549/f94a9001-559d-46b5-9d94-e69fbdc030ee/public/cluster-1/030223203100.json"},
{"id": "12-0", "title": "Area Outage", "desc": {"n_out": 1, "cust_a": {"val": 4, "mask": 5}, "inc_id": null, "crew_status": null, "cluster": false, "etr": "2023-10-25T15:00:00Z", "etr_confidence": null, "comments": null, "cause": {"EN-US": "Pending crew assessment", "orig": "NOCAUSE"}, "crew_icon": false, "start_time": "2023-10-24T14:20:36Z", "lastFileUpdate": "2023-10-24T15:50:07.591Z"}, "geom": {"p": ["w`ubGpj{zN"]}, "source": "https://kubra.io/cluster-data/101/227de1f9-4adc-4fc9-98cb-dc2b847c0549/f94a9001-559d-46b5-9d94-e69fbdc030ee/public/cluster-1/030223203101.json"},
{"id": "12-1", "title": "Area Outage", "desc": {"n_out": 1, "cust_a": {"val": 4, "mask": 5}, "inc_id": null, "crew_status": null, "cluster": false, "etr": "2023-10-25T15:45:00Z", "etr_confidence": null, "comments": null, "cause": {"EN-US": "Reqd to repair/upgrade equip", "orig": "PLANNED INTENTIONAL"}, "crew_icon": false, "start_time": "2023-10-24T15:09:42.477Z", "lastFileUpdate": "2023-10-24T15:50:07.591Z"}, "geom": {"p": ["giqbG~}}zN"]}, "source": "https://kubra.io/cluster-data/101/227de1f9-4adc-4fc9-98cb-dc2b847c0549/f94a9001-559d-46b5-9d94-e69fbdc030ee/public/cluster-1/030223203101.json"},
{"id": "12-0", "title": "Area Outage", "desc": {"n_out": 1, "cust_a": {"val": 4, "mask": 5}, "inc_id": null, "crew_status": null, "cluster": false, "etr": "2023-10-24T16:00:00Z", "etr_confidence": null, "comments": null, "cause": {"EN-US": "Pending crew assessment", "orig": "NOCAUSE"}, "crew_icon": false, "start_time": "2023-10-22T00:38:50Z", "lastFileUpdate": "2023-10-24T15:50:07.591Z"}, "geom": {"p": ["{k`bGlsd{N"]}, "source": "https://kubra.io/cluster-data/201/227de1f9-4adc-4fc9-98cb-dc2b847c0549/f94a9001-559d-46b5-9d94-e69fbdc030ee/public/cluster-1/030223203102.json"},
{"id": "12-1", "title": "Area Outage", "desc": {"n_out": 1, "cust_a": {"val": 4, "mask": 5}, "inc_id": null, "crew_status": null, "cluster": false, "etr": "2023-10-25T15:30:00Z", "etr_confidence": null, "comments": null, "cause": {"EN-US": "Pending crew assessment", "orig": "NOCAUSE"}, "crew_icon": false, "start_time": "2023-10-24T14:49:18Z", "lastFileUpdate": "2023-10-24T15:50:07.591Z"}, "geom": {"p": ["yf}aGnpa{N"]}, "source": "https://kubra.io/cluster-data/201/227de1f9-4adc-4fc9-98cb-dc2b847c0549/f94a9001-559d-46b5-9d94-e69fbdc030ee/public/cluster-1/030223203102.json"},
{"id": "12-0", "title": "Area Outage", "desc": {"n_out": 1, "cust_a": {"val": 4, "mask": 5}, "inc_id": null, "crew_status": null, "cluster": false, "etr": "ETR-NULL", "etr_confidence": null, "comments": "Power problem is being assessed. A restoration estimate is in progress.", "cause": {"EN-US": "Pending crew assessment", "orig": "NOCAUSE"}, "crew_icon": false, "start_time": "2023-10-24T15:35:26Z", "lastFileUpdate": "2023-10-24T15:50:07.591Z"}, "geom": {"p": ["cb`bG~bszN"]}, "source": "https://kubra.io/cluster-data/301/227de1f9-4adc-4fc9-98cb-dc2b847c0549/f94a9001-559d-46b5-9d94-e69fbdc030ee/public/cluster-1/030223203103.json"},
{"id": "12-1", "title": "Area Outage", "desc": {"n_out": 1, "cust_a": {"val": 4, "mask": 5}, "inc_id": null, "crew_status": null, "cluster": false, "etr": "2023-10-25T13:45:00Z", "etr_confidence": null, "comments": null, "cause": {"EN-US": "Pending crew assessment", "orig": "NOCAUSE"}, "crew_icon": false, "start_time": "2023-10-24T13:00:57Z", "lastFileUpdate": "2023-10-24T15:50:07.591Z"}, "geom": {"p": ["so`bG~a}zN"]}, "source": "https://kubra.io/cluster-data/301/227de1f9-4adc-4fc9-98cb-dc2b847c0549/f94a9001-559d-46b5-9d94-e69fbdc030ee/public/cluster-1/030223203103.json"},
{"id": "12-2", "title": "Area Outage", "desc": {"n_out": 1, "cust_a": {"val": 4, "mask": 5}, "inc_id": null, "crew_status": null, "cluster": false, "etr": "2023-10-24T21:15:00Z", "etr_confidence": null, "comments": null, "cause": {"EN-US": "Reqd to repair/upgrade equip", "orig": "PLANNED INTENTIONAL"}, "crew_icon": false, "start_time": "2023-10-24T14:28:36Z", "lastFileUpdate": "2023-10-24T15:50:07.591Z"}, "geom": {"p": ["ku_bGl`wzN"]}, "source": "https://kubra.io/cluster-data/301/227de1f9-4adc-4fc9-98cb-dc2b847c0549/f94a9001-559d-46b5-9d94-e69fbdc030ee/public/cluster-1/030223203103.json"},
{"id": "12-3", "title": "Area Outage", "desc": {"n_out": 1, "cust_a": {"val": 4, "mask": 5}, "inc_id": null, "crew_status": null, "cluster": false, "etr": "2023-10-25T14:00:00Z", "etr_confidence": null, "comments": null, "cause": {"EN-US": "Equipment problem", "orig": "EQUIPMENT FAILURE"}, "crew_icon": false, "start_time": "2023-10-24T13:24:51.188Z", "lastFileUpdate": "2023-10-24T15:50:07.591Z"}, "geom": {"p": ["}hbbG~gxzN"]}, "source": "https://kubra.io/cluster-data/301/227de1f9-4adc-4fc9-98cb-dc2b847c0549/f94a9001-559d-46b5-9d94-e69fbdc030ee/public/cluster-1/030223203103.json"},
{"id": "12-4", "title": "Area Outage", "desc": {"n_out": 1, "cust_a": {"val": 4, "mask": 5}, "inc_id": null, "crew_status": null, "cluster": false, "etr": "2023-10-25T03:15:00Z", "etr_confidence": null, "comments": null, "cause": {"EN-US": "Pending crew assessment", "orig": "NOCAUSE"}, "crew_icon": false, "start_time": "2023-10-23T22:15:57Z", "lastFileUpdate": "2023-10-24T15:50:07.591Z"}, "geom": {"p": ["gi}aGxj{zN"]}, "source": "https://kubra.io/cluster-data/301/227de1f9-4adc-4fc9-98cb-dc2b847c0549/f94a9001-559d-46b5-9d94-e69fbdc030ee/public/cluster-1/030223203103.json"},
{"id": "12-0", "title": "Area Outage", "desc": {"n_out": 1, "cust_a": {"val": 4, "mask": 5}, "inc_id": null, "crew_status": null, "cluster": false, "etr": "2023-10-25T03:00:00Z", "etr_confidence": null, "comments": null, "cause": {"EN-US": "Pending crew assessment", "orig": "NOCAUSE"}, "crew_icon": false, "start_time": "2023-10-23T16:54:38Z", "lastFileUpdate": "2023-10-24T15:50:07.591Z"}, "geom": {"p": ["_babGtmmzN"]}, "source": "https://kubra.io/cluster-data/211/227de1f9-4adc-4fc9-98cb-dc2b847c0549/f94a9001-559d-46b5-9d94-e69fbdc030ee/public/cluster-1/030223203112.json"},
{"id": "12-1", "title": "Area Outage", "desc": {"n_out": 1, "cust_a": {"val": 4, "mask": 5}, "inc_id": null, "crew_status": null, "cluster": false, "etr": "ETR-NULL", "etr_confidence": null, "comments": "Power problem is being assessed. A restoration estimate is in progress.", "cause": {"EN-US": "No problem upon crew arrival", "orig": "NO ISSUES FOUND"}, "crew_icon": false, "start_time": "2023-10-23T14:34:46Z", "lastFileUpdate": "2023-10-24T15:50:07.591Z"}, "geom": {"p": ["y``bGtz`zN"]}, "source": "https://kubra.io/cluster-data/211/227de1f9-4adc-4fc9-98cb-dc2b847c0549/f94a9001-559d-46b5-9d94-e69fbdc030ee/public/cluster-1/030223203112.json"},
{"id": "12-2", "title": "Area Outage", "desc": {"n_out": 1, "cust_a": {"val": 4, "mask": 5}, "inc_id": null, "crew_status": null, "cluster": false, "etr": "2023-10-25T16:15:00Z", "etr_confidence": null, "comments": null, "cause": {"EN-US": "Equipment problem", "orig": "EQUIPMENT FAILURE"}, "crew_icon": false, "start_time": "2023-10-23T19:21:11Z", "lastFileUpdate": "2023-10-24T15:50:07.591Z"}, "geom": {"p": ["ubbbGvcazN"]}, "source": "https://kubra.io/cluster-data/211/227de1f9-4adc-4fc9-98cb-dc2b847c0549/f94a9001-559d-46b5-9d94-e69fbdc030ee/public/cluster-1/030223203112.json"},
{"id": "13-0", "title": "Area Outage", "desc": {"n_out": 1, "cust_a": {"val": 4, "mask": 5}, "inc_id": null, "crew_status": null, "cluster": false, "etr": "2023-10-25T04:45:00Z", "etr_confidence": null, "comments": null, "cause": {"EN-US": "No problem upon crew arrival", "orig": "NO ISSUES FOUND"}, "crew_icon": false, "start_time": "2023-10-23T23:48:59Z", "lastFileUpdate": "2023-10-24T15:50:07.591Z"}, "geom": {"p": ["{e~aGnjvyN"]}, "source": "https://kubra.io/cluster-data/231/227de1f9-4adc-4fc9-98cb-dc2b847c0549/f94a9001-559d-46b5-9d94-e69fbdc030ee/public/cluster-1/0302232031132.json"},
{"id": "14-0", "title": "Area Outage", "desc": {"n_out": 1, "cust_a": {"val": 4, "mask": 5}, "inc_id": null, "crew_status": null, "cluster": false, "etr": "2023-10-24T21:30:00Z", "etr_confidence": null, "comments": null, "cause": {"EN-US": "Reqd to repair/upgrade equip", "orig": "PLANNED INTENTIONAL"}, "crew_icon": false, "start_time": "2023-10-24T14:44:07.205Z", "lastFileUpdate": "2023-10-24T15:50:07.591Z"}, "geom": {"p": ["yjabGvqnyN"]}, "source": "https://kubra.io/cluster-data/133/227de1f9-4adc-4fc9-98cb-dc2b847c0549/f94a9001-559d-46b5-9d94-e69fbdc030ee/public/cluster-1/03022320311331.json"},
{"id": "14-1", "title": "Area Outage", "desc": {"n_out": 1, "cust_a": {"val": 4, "mask": 5}, "inc_id": null, "crew_status": null, "cluster": false, "etr": "2023-10-25T16:00:00Z", "etr_confidence": null, "comments": null, "cause": {"EN-US": "Pending crew assessment", "orig": "NOCAUSE"}, "crew_icon": false, "start_time": "2023-10-24T15:16:44.121Z", "lastFileUpdate": "2023-10-24T15:50:07.591Z"}, "geom": {"p": ["esbbGxlmyN"]}, "source": "https://kubra.io/cluster-data/133/227de1f9-4adc-4fc9-98cb-dc2b847c0549/f94a9001-559d-46b5-9d94-e69fbdc030ee/public/cluster-1/03022320311331.json"},
{"id": "14-0", "title": "Area Outage", "desc": {"n_out": 2, "cust_a": {"val": 6}, "inc_id": null, "crew_status": null, "cluster": true, "etr": "2023-10-25T14:30:00Z", "etr_confidence": null, "outages": [{"cust_a": {"val": 4, "mask": 5}, "crew_icon": false, "etr": "2023-10-25T14:30:00Z", "cause": {"EN-US": "Reqd to repair/upgrade equip", "orig": "PLANNED INTENTIONAL"}, "start_time": "2023-10-24T13:59:08.418Z", "lastFileUpdate": "2023-10-24T15:50:07.591Z"}, {"cust_a": {"val": 5}, "crew_icon": false, "etr": "2023-10-24T21:45:00Z", "cause": {"EN-US": "Pending crew assessment", "orig": "NOCAUSE"}, "start_time": "2023-10-24T14:50:46Z", "lastFileUpdate": "2023-10-24T15:50:07.591Z"}], "comments": null, "cause": null, "crew_icon": false, "start_time": "2023-10-24T13:59:08.418Z"}, "geom": {"p": ["wd}aGtboyN"]}, "source": "https://kubra.io/cluster-data/333/227de1f9-4adc-4fc9-98cb-dc2b847c0549/f94a9001-559d-46b5-9d94-e69fbdc030ee/public/cluster-1/03022320311333.json"},
{"id": "12-0", "title": "Area Outage", "desc": {"n_out": 1, "cust_a": {"val": 4, "mask": 5}, "inc_id": null, "crew_status": null, "cluster": false, "etr": "ETR-EXP", "etr_confidence": null, "comments": null, "cause": {"EN-US": "Problem with customer equipment", "orig": "CUSTOMER EQUIPMENT"}, "crew_icon": false, "start_time": "2023-10-22T16:29:56Z", "lastFileUpdate": "2023-10-24T15:50:07.591Z"}, "geom": {"p": ["a{qaG`aa{N"]}, "source": "https://kubra.io/cluster-data/021/227de1f9-4adc-4fc9-98cb-dc2b847c0549/f94a9001-559d-46b5-9d94-e69fbdc030ee/public/cluster-1/030223203120.json"},
{"id": "12-1", "title": "Area Outage", "desc": {"n_out": 1, "cust_a": {"val": 4, "mask": 5}, "inc_id": null, "crew_status": null, "cluster": false, "etr": "2023-10-25T02:45:00Z", "etr_confidence": null, "comments": null, "cause": {"EN-US": "No problem upon crew arrival", "orig": "NO ISSUES FOUND"}, "crew_icon": false, "start_time": "2023-10-23T18:01:25Z", "lastFileUpdate": "2023-10-24T15:50:07.591Z"}, "geom": {"p": ["uyyaGtph{N"]}, "source": "https://kubra.io/cluster-data/021/227de1f9-4adc-4fc9-98cb-dc2b847c0549/f94a9001-559d-46b5-9d94-e69fbdc030ee/public/cluster-1/030223203120.json"},
{"id": "12-0", "title": "Area Outage", "desc": {"n_out": 1, "cust_a": {"val": 4, "mask": 5}, "inc_id": null, "crew_status": null, "cluster": false, "etr": "2023-10-25T15:45:00Z", "etr_confidence": null, "comments": null, "cause": {"EN-US": "Pending crew assessment", "orig": "NOCAUSE"}, "crew_icon": false, "start_time": "2023-10-23T19:54:09Z", "lastFileUpdate": "2023-10-24T15:50:07.591Z"}, "geom": {"p": ["qtyaG||zzN"]}, "source": "https://kubra.io/cluster-data/121/227de1f9-4adc-4fc9-98cb-dc2b847c0549/f94a9001-559d-46b5-9d94-e69fbdc030ee/public/cluster-1/030223203121.json"},
{"id": "12-1", "title": "Area Outage", "desc": {"n_out": 1, "cust_a": {"val": 4, "mask": 5}, "inc_id": null, "crew_status": null, "cluster": false, "etr": "ETR-NULL", "etr_confidence": null, "comments": "Power problem is being assessed. A restoration estimate is in progress.", "cause": {"EN-US": "Pending crew assessment", "orig": "NOCAUSE"}, "crew_icon": false, "start_time": "2023-10-24T15:22:16Z", "lastFileUpdate": "2023-10-24T15:50:07.591Z"}, "geom": {"p": ["q}zaGffozN"]}, "source": "https://kubra.io/cluster-data/121/227de1f9-4adc-4fc9-98cb-dc2b847c0549/f94a9001-559d-46b5-9d94-e69fbdc030ee/public/cluster-1/030223203121.json"},
{"id": "12-2", "title": "Area Outage", "desc": {"n_out": 1, "cust_a": {"val": 4, "mask": 5}, "inc_id": null, "crew_status": null, "cluster": false, "etr": "2023-10-25T15:30:00Z", "etr_confidence": null, "comments": null, "cause": {"EN-US": "Pending crew assessment", "orig": "NOCAUSE"}, "crew_icon": false, "start_time": "2023-10-24T14:50:02Z", "lastFileUpdate": "2023-10-24T15:50:07.591Z"}, "geom": {"p": ["myraGxpzzN"]}, "source": "https://kubra.io/cluster-data/121/227de1f9-4adc-4fc9-98cb-dc2b847c0549/f94a9001-559d-46b5-9d94-e69fbdc030ee/public/cluster-1/030223203121.json"},
{"id": "12-0", "title": "Area Outage", "desc": {"n_out": 1, "cust_a": {"val": 4, "mask": 5}, "inc_id": null, "crew_status": null, "cluster": false, "etr": "2023-10-24T17:30:00Z", "etr_confidence": null, "comments": null, "cause": {"EN-US": "Damage caused by trees", "orig": "TREEIROW"}, "crew_icon": false, "start_time": "2023-10-22T21:23:32Z", "lastFileUpdate": "2023-10-24T15:50:07.591Z"}, "geom": {"p": ["}njaGt~i{N"]}, "source": "https://kubra.io/cluster-data/221/227de1f9-4adc-4fc9-98cb-dc2b847c0549/f94a9001-559d-46b5-9d94-e69fbdc030ee/public/cluster-1/030223203122.json"},
{"id": "12-1", "title": "Area Outage", "desc": {"n_out": 1, "cust_a": {"val": 4, "mask": 5}, "inc_id": null, "crew_status": null, "cluster": false, "etr": "2023-10-25T13:15:00Z", "etr_confidence": null, "comments": null, "cause": {"EN-US": "Pending crew assessment", "orig": "NOCAUSE"}, "crew_icon": false, "start_time": "2023-10-22T22:18:39Z", "lastFileUpdate": "2023-10-24T15:50:07.591Z"}, "geom": {"p": ["}jlaGjao{N"]}, "source": "https://kubra.io/cluster-data/221/227de1f9-4adc-4fc9-98cb-dc2b847c0549/f94a9001-559d-46b5-9d94-e69fbdc030ee/public/cluster-1/030223203122.json"},
{"id": "12-0", "title": "Area Outage", "desc": {"n_out": 1, "cust_a": {"val": 4, "mask": 5}, "inc_id": null, "crew_status": null, "cluster": false, "etr": "2023-10-25T03:15:00Z", "etr_confidence": null, "comments": null, "cause": {"EN-US": "Pending crew assessment", "orig": "NOCAUSE"}, "crew_icon": false, "start_time": "2023-10-23T22:24:42Z", "lastFileUpdate": "2023-10-24T15:50:07.591Z"}, "geom": {"p": ["opmaG`ftzN"]}, "source": "https://kubra.io/cluster-data/321/227de1f9-4adc-4fc9-98cb-dc2b847c0549/f94a9001-559d-46b5-9d94-e69fbdc030ee/public/cluster-1/030223203123.json"},
{"id": "12-1", "title": "Area Outage", "desc": {"n_out": 1, "cust_a": {"val": 4, "mask": 5}, "inc_id": null, "crew_status": null, "cluster": false, "etr": "ETR-EXP", "etr_confidence": null, "comments": null, "cause": {"EN-US": "Equipment problem", "orig": "EQUIPMENT FAILURE"}, "crew_icon": false, "start_time": "2023-10-21T22:25:15Z", "lastFileUpdate": "2023-10-24T15:50:07.591Z"}, "geom": {"p": ["{apaG`p{zN"]}, "source": "https://kubra.io/cluster-data/321/227de1f9-4adc-4fc9-98cb-dc2b847c0549/f94a9001-559d-46b5-9d94-e69fbdc030ee/public/cluster-1/030223203123.json"},
{"id": "11-0", "title": "Area Outage", "desc": {"n_out": 1, "cust_a": {"val": 4, "mask": 5}, "inc_id": null, "crew_status": null, "cluster": false, "etr": "2023-10-25T13:30:00Z", "etr_confidence": null, "comments": null, "cause": {"EN-US": "Equipment problem", "orig": "EQUIPMENT FAILURE"}, "crew_icon": false, "start_time": "2023-10-24T12:53:01.748Z", "lastFileUpdate": "2023-10-24T15:50:07.591Z"}, "geom": {"p": ["uyqaGxkvyN"]}, "source": "https://kubra.io/cluster-data/313/227de1f9-4adc-4fc9-98cb-dc2b847c0549/f94a9001-559d-46b5-9d94-e69fbdc030ee/public/cluster-1/03022320313.json"},
{"id": "11-1", "title": "Area Outage", "desc": {"n_out": 1, "cust_a": {"val": 4, "mask": 5}, "inc_id": null, "crew_status": null, "cluster": false, "etr": "2023-10-25T03:15:00Z", "etr_confidence": null, "comments": null, "cause": {"EN-US": "Pending crew assessment", "orig": "NOCAUSE"}, "crew_icon": false, "start_time": "2023-10-23T22:10:08Z", "lastFileUpdate": "2023-10-24T15:50:07.591Z"}, "geom": {"p": ["sqqaGdsmyN"]}, "source": "https://kubra.io/cluster-data/313/227de1f9-4adc-4fc9-98cb-dc2b847c0549/f94a9001-559d-46b5-9d94-e69fbdc030ee/public/cluster-1/03022320313.json"},
{"id": "11-2", "title": "Area Outage", "desc": {"n_out": 1, "cust_a": {"val": 4, "mask": 5}, "inc_id": null, "crew_status": null, "cluster": false, "etr": "2023-10-25T01:15:00Z", "etr_confidence": null, "comments": null, "cause": {"EN-US": "Private prop tree damaged equip", "orig": "TREEBROW"}, "crew_icon": false, "start_time": "2023-10-23T20:24:25Z", "lastFileUpdate": "2023-10-24T15:50:07.591Z"}, "geom": {"p": ["w}zaGxs{yN"]}, "source": "https://kubra.io/cluster-data/313/227de1f9-4adc-4fc9-98cb-dc2b847c0549/f94a9001-559d-46b5-9d94-e69fbdc030ee/public/cluster-1/03022320313.json"},
{"id": "11-3", "title": "Area Outage", "desc": {"n_out": 1, "cust_a": {"val": 4, "mask": 5}, "inc_id": null, "crew_status": null, "cluster": false, "etr": "2023-10-25T15:45:00Z", "etr_confidence": null, "comments": null, "cause": {"EN-US": "Pending crew assessment", "orig": "NOCAUSE"}, "crew_icon": false, "start_time": "2023-10-24T15:04:15Z", "lastFileUpdate": "2023-10-24T15:50:07.591Z"}, "geom": {"p": ["enyaGh}myN"]}, "source": "https://kubra.io/cluster-data/313/227de1f9-4adc-4fc9-98cb-dc2b847c0549/f94a9001-559d-46b5-9d94-e69fbdc030ee/public/cluster-1/03022320313.json"},
{"id": "11-4", "title": "Area Outage", "desc": {"n_out": 1, "cust_a": {"val": 4, "mask": 5}, "inc_id": null, "crew_status": null, "cluster": false, "etr": "2023-10-25T15:00:00Z", "etr_confidence": null, "comments": null, "cause": {"EN-US": "Reqd to repair/upgrade equip", "orig": "PLANNED INTENTIONAL"}, "crew_icon": false, "start_time": "2023-10-24T14:24:56Z", "lastFileUpdate": "2023-10-24T15:50:07.591Z"}, "geom": {"p": ["{egaGpgezN"]}, "source": "https://kubra.io/cluster-data/313/227de1f9-4adc-4fc9-98cb-dc2b847c0549/f94a9001-559d-46b5-9d94-e69fbdc030ee/public/cluster-1/03022320313.json"},
{"id": "11-5", "title": "Area Outage", "desc": {"n_out": 1, "cust_a": {"val": 4, "mask": 5}, "inc_id": null, "crew_status": null, "cluster": false, "etr": "2023-10-25T14:30:00Z", "etr_confidence": null, "comments": null, "cause": {"EN-US": "Pending crew assessment", "orig": "NOCAUSE"}, "crew_icon": false, "start_time": "2023-10-24T13:45:16Z", "lastFileUpdate": "2023-10-24T15:50:07.591Z"}, "geom": {"p": ["msmaGxm}yN"]}, "source": "https://kubra.io/cluster-data/313/227de1f9-4adc-4fc9-98cb-dc2b847c0549/f94a9001-559d-46b5-9d94-e69fbdc030ee/public/cluster-1/03022320313.json"},
{"id": "11-6", "title": "Area Outage", "desc": {"n_out": 1, "cust_a": {"val": 4, "mask": 5}, "inc_id": null, "crew_status": null, "cluster": false, "etr": "ETR-NULL", "etr_confidence": null, "comments": "Power problem is being assessed. A restoration estimate is in progress.", "cause": {"EN-US": "Reqd to repair/upgrade equip", "orig": "PLANNED INTENTIONAL"}, "crew_icon": false, "start_time": "2023-10-24T15:43:54.454Z", "lastFileUpdate": "2023-10-24T15:50:07.591Z"}, "geom": {"p": ["wuoaGtxqyN"]}, "source": "https://kubra.io/cluster-data/313/227de1f9-4adc-4fc9-98cb-dc2b847c0549/f94a9001-559d-46b5-9d94-e69fbdc030ee/public/cluster-1/03022320313.json"},
{"id": "11-7", "title": "Area Outage", "desc": {"n_out": 1, "cust_a": {"val": 4, "mask": 5}, "inc_id": null, "crew_status": null, "cluster": false, "etr": "2023-10-25T14:15:00Z", "etr_confidence": null, "comments": null, "cause": {"EN-US": "Pending crew assessment", "orig": "NOCAUSE"}, "crew_icon": false, "start_time": "2023-10-24T13:37:13Z", "lastFileUpdate": "2023-10-24T15:50:07.591Z"}, "geom": {"p": ["{gsaGtdazN"]}, "source": "https://kubra.io/cluster-data/313/227de1f9-4adc-4fc9-98cb-dc2b847c0549/f94a9001-559d-46b5-9d94-e69fbdc030ee/public/cluster-1/03022320313.json"},
{"id": "11-8", "title": "Area Outage", "desc": {"n_out": 1, "cust_a": {"val": 4, "mask": 5}, "inc_id": null, "crew_status": null, "cluster": false, "etr": "2023-10-25T14:00:00Z", "etr_confidence": null, "comments": null, "cause": {"EN-US": "Equipment problem", "orig": "EQUIPMENT FAILURE"}, "crew_icon": false, "start_time": "2023-10-23T13:16:09Z", "lastFileUpdate": "2023-10-24T15:50:07.591Z"}, "geom": {"p": ["}t{aGfpdzN"]}, "source": "https://kubra.io/cluster-data/313/227de1f9-4adc-4fc9-98cb-dc2b847c0549/f94a9001-559d-46b5-9d94-e69fbdc030ee/public/cluster-1/03022320313.json"},
{"id": "11-9", "title": "Area Outage", "desc": {"n_out": 1, "cust_a": {"val": 4, "mask": 5}, "inc_id": null, "crew_status": null, "cluster": false, "etr": "2023-10-25T08:00:00Z", "etr_confidence": null, "comments": null, "cause": {"EN-US": "Pending crew assessment", "orig": "NOCAUSE"}, "crew_icon": false, "start_time": "2023-10-24T02:57:05Z", "lastFileUpdate": "2023-10-24T15:50:07.591Z"}, "geom": {"p": ["qruaG|cgzN"]}, "source": "https://kubra.io/cluster-data/313/227de1f9-4adc-4fc9-98cb-dc2b847c0549/f94a9001-559d-46b5-9d94-e69fbdc030ee/public/cluster-1/03022320313.json"},
{"id": "12-0", "title": "Area Outage", "desc": {"n_out": 1, "cust_a": {"val": 4, "mask": 5}, "inc_id": null, "crew_status": null, "cluster": false, "etr": "2023-10-24T17:45:00Z", "etr_confidence": null, "comments": null, "cause": {"EN-US": "Problem with customer equipment", "orig": "CUSTOMER EQUIPMENT"}, "crew_icon": false, "start_time": "2023-10-23T05:04:12Z", "lastFileUpdate": "2023-10-24T15:50:07.591Z"}, "geom": {"p": ["usaaGlfb{N"]}, "source": "https://kubra.io/cluster-data/003/227de1f9-4adc-4fc9-98cb-dc2b847c0549/f94a9001-559d-46b5-9d94-e69fbdc030ee/public/cluster-1/030223203300.json"},
{"id": "13-0", "title": "Area Outage", "desc": {"n_out": 1, "cust_a": {"val": 22}, "inc_id": null, "crew_status": null, "cluster": false, "etr": "2023-10-24T20:45:00Z", "etr_confidence": null, "comments": null, "cause": {"EN-US": "Reqd to repair/upgrade equip", "orig": "PLANNED INTENTIONAL"}, "crew_icon": false, "start_time": "2023-10-24T14:01:29.182Z", "lastFileUpdate": "2023-10-24T15:50:07.591Z"}, "geom": {"a": ["}h_aGnevzNk@zAy@i@aAq@gA{@m@i@l@aBdBZxBrCNV"], "p": ["im_aGncvzN"]}, "source": "https://kubra.io/cluster-data/110/227de1f9-4adc-4fc9-98cb-dc2b847c0549/f94a9001-559d-46b5-9d94-e69fbdc030ee/public/cluster-1/0302232033011.json"},
{"id": "13-1", "title": "Area Outage", "desc": {"n_out": 1, "cust_a": {"val": 4, "mask": 5}, "inc_id": null, "crew_status": null, "cluster": false, "etr": "2023-10-25T03:00:00Z", "etr_confidence": null, "comments": null, "cause": {"EN-US": "Pending crew assessment", "orig": "NOCAUSE"}, "crew_icon": false, "start_time": "2023-10-23T22:00:07Z", "lastFileUpdate": "2023-10-24T15:50:07.591Z"}, "geom": {"p": ["y__aGdxqzN"]}, "source": "https://kubra.io/cluster-data/110/227de1f9-4adc-4fc9-98cb-dc2b847c0549/f94a9001-559d-46b5-9d94-e69fbdc030ee/public/cluster-1/0302232033011.json"},
{"id": "13-2", "title": "Area Outage", "desc": {"n_out": 1, "cust_a": {"val": 4, "mask": 5}, "inc_id": null, "crew_status": null, "cluster": false, "etr": "2023-10-25T15:45:00Z", "etr_confidence": null, "comments": null, "cause": {"EN-US": "Pending crew assessment", "orig": "NOCAUSE"}, "crew_icon": false, "start_time": "2023-10-24T15:04:55Z", "lastFileUpdate": "2023-10-24T15:50:07.591Z"}, "geom": {"p": ["{_~`G~sqzN"]}, "source": "https://kubra.io/cluster-data/110/227de1f9-4adc-4fc9-98cb-dc2b847c0549/f94a9001-559d-46b5-9d94-e69fbdc030ee/public/cluster-1/0302232033011.json"},
{"id": "13-0", "title": "Area Outage", "desc": {"n_out": 1, "cust_a": {"val": 4, "mask": 5}, "inc_id": null, "crew_status": null, "cluster": false, "etr": "2023-10-25T15:15:00Z", "etr_confidence": null, "comments": null, "cause": {"EN-US": "Reqd to repair/upgrade equip", "orig": "PLANNED INTENTIONAL"}, "crew_icon": false, "start_time": "2023-10-24T14:35:03Z", "lastFileUpdate": "2023-10-24T15:50:07.591Z"}, "geom": {"p": ["}c{`GrhyzN"]}, "source": "https://kubra.io/cluster-data/210/227de1f9-4adc-4fc9-98cb-dc2b847c0549/f94a9001-559d-46b5-9d94-e69fbdc030ee/public/cluster-1/0302232033012.json"},
{"id": "14-0", "title": "Area Outage", "desc": {"n_out": 3, "cust_a": {"val": 13}, "inc_id": null, "crew_status": null, "cluster": true, "etr": "2023-10-24T22:00:00Z", "etr_confidence": null, "outages": [{"cust_a": {"val": 4, "mask": 5}, "crew_icon": false, "etr": "2023-10-24T22:00:00Z", "cause": {"EN-US": "Pending crew assessment", "orig": "NOCAUSE"}, "start_time": "2023-10-24T15:00:33Z", "lastFileUpdate": "2023-10-24T15:50:07.591Z"}, {"cust_a": {"val": 4, "mask": 5}, "crew_icon": false, "etr": "2023-10-24T22:00:00Z", "cause": {"EN-US": "Pending crew assessment", "orig": "NOCAUSE"}, "start_time": "2023-10-24T15:00:31Z", "lastFileUpdate": "2023-10-24T15:50:07.591Z"}, {"cust_a": {"val": 9}, "crew_icon": false, "etr": "2023-10-24T22:00:00Z", "cause": {"EN-US": "Reqd to repair/upgrade equip", "orig": "PLANNED INTENTIONAL"}, "start_time": "2023-10-24T15:00:30Z", "lastFileUpdate": "2023-10-24T15:50:07.591Z"}], "comments": null, "cause": null, "crew_icon": false, "start_time": "2023-10-24T15:00:30Z"}, "geom": {"p": ["o}|`GzpszN"]}, "source": "https://kubra.io/cluster-data/031/227de1f9-4adc-4fc9-98cb-dc2b847c0549/f94a9001-559d-46b5-9d94-e69fbdc030ee/public/cluster-1/03022320330130.json"},
{"id": "14-0", "title": "Area Outage", "desc": {"n_out": 2, "cust_a": {"val": 15}, "inc_id": null, "crew_status": null, "cluster": true, "etr": "2023-10-25T15:15:00Z", "etr_confidence": null, "outages": [{"cust_a": {"val": 14}, "crew_icon": false, "etr": "2023-10-24T21:30:00Z", "cause": {"EN-US": "Pending crew assessment", "orig": "NOCAUSE"}, "start_time": "2023-10-24T14:37:19Z", "lastFileUpdate": "2023-10-24T15:50:07.591Z"}, {"cust_a": {"val": 4, "mask": 5}, "crew_icon": false, "etr": "2023-10-25T15:15:00Z", "cause": {"EN-US": "Pending crew assessment", "orig": "NOCAUSE"}, "start_time": "2023-10-24T14:41:36Z", "lastFileUpdate": "2023-10-24T15:50:07.591Z"}], "comments": null, "cause": null, "crew_icon": false, "start_time": "2023-10-24T14:37:19Z"}, "geom": {"p": ["sew`G`xrzN"]}, "source": "https://kubra.io/cluster-data/231/227de1f9-4adc-4fc9-98cb-dc2b847c0549/f94a9001-559d-46b5-9d94-e69fbdc030ee/public/cluster-1/03022320330132.json"},
{"id": "12-0", "title": "Area Outage", "desc": {"n_out": 1, "cust_a": {"val": 4, "mask": 5}, "inc_id": null, "crew_status": null, "cluster": false, "etr": "2023-10-24T17:30:00Z", "etr_confidence": null, "comments": null, "cause": {"EN-US": "Equipment problem", "orig": "EQUIPMENT FAILURE"}, "crew_icon": false, "start_time": "2023-10-23T22:28:45Z", "lastFileUpdate": "2023-10-24T15:50:07.591Z"}, "geom": {"p": ["au}`GvbmzN"]}, "source": "https://kubra.io/cluster-data/013/227de1f9-4adc-4fc9-98cb-dc2b847c0549/f94a9001-559d-46b5-9d94-e69fbdc030ee/public/cluster-1/030223203310.json"},
{"id": "12-1", "title": "Area Outage", "desc": {"n_out": 1, "cust_a": {"val": 4, "mask": 5}, "inc_id": null, "crew_status": null, "cluster": false, "etr": "2023-10-25T13:45:00Z", "etr_confidence": null, "comments": null, "cause": {"EN-US": "No problem upon crew arrival", "orig": "NO ISSUES FOUND"}, "crew_icon": false, "start_time": "2023-10-23T00:40:16Z", "lastFileUpdate": "2023-10-24T15:50:07.591Z"}, "geom": {"p": ["ir_aGp}kzN"]}, "source": "https://kubra.io/cluster-data/013/227de1f9-4adc-4fc9-98cb-dc2b847c0549/f94a9001-559d-46b5-9d94-e69fbdc030ee/public/cluster-1/030223203310.json"},
{"id": "12-0", "title": "Area Outage", "desc": {"n_out": 1, "cust_a": {"val": 4, "mask": 5}, "inc_id": null, "crew_status": null, "cluster": false, "etr": "2023-10-24T20:45:00Z", "etr_confidence": null, "comments": null, "cause": {"EN-US": "Pending crew assessment", "orig": "NOCAUSE"}, "crew_icon": false, "start_time": "2023-10-24T14:02:32Z", "lastFileUpdate": "2023-10-24T15:50:07.591Z"}, "geom": {"a": ["{fg`G~ek{NgA`CI{ApAe@"], "p": ["ohg`Gvgk{N"]}, "source": "https://kubra.io/cluster-data/023/227de1f9-4adc-4fc9-98cb-dc2b847c0549/f94a9001-559d-46b5-9d94-e69fbdc030ee/public/cluster-1/030223203320.json"},
{"id": "12-1", "title": "Area Outage", "desc": {"n_out": 1, "cust_a": {"val": 4, "mask": 5}, "inc_id": null, "crew_status": null, "cluster": false, "etr": "2023-10-25T13:15:00Z", "etr_confidence": null, "comments": null, "cause": {"EN-US": "No problem upon crew arrival", "orig": "NO ISSUES FOUND"}, "crew_icon": false, "start_time": "2023-10-24T12:31:53Z", "lastFileUpdate": "2023-10-24T15:50:07.591Z"}, "geom": {"p": ["us``Ghig{N"]}, "source": "https://kubra.io/cluster-data/023/227de1f9-4adc-4fc9-98cb-dc2b847c0549/f94a9001-559d-46b5-9d94-e69fbdc030ee/public/cluster-1/030223203320.json"},
{"id": "12-2", "title": "Area Outage", "desc": {"n_out": 1, "cust_a": {"val": 4, "mask": 5}, "inc_id": null, "crew_status": null, "cluster": false, "etr": "2023-10-25T13:00:00Z", "etr_confidence": null, "comments": null, "cause": {"EN-US": "No problem upon crew arrival", "orig": "NO ISSUES FOUND"}, "crew_icon": false, "start_time": "2023-10-24T12:27:20Z", "lastFileUpdate": "2023-10-24T15:50:07.591Z"}, "geom": {"p": ["wcb`Ghji{N"]}, "source": "https://kubra.io/cluster-data/023/227de1f9-4adc-4fc9-98cb-dc2b847c0549/f94a9001-559d-46b5-9d94-e69fbdc030ee/public/cluster-1/030223203320.json"},
{"id": "9-0", "title": "Area Outage", "desc": {"n_out": 1, "cust_a": {"val": 4, "mask": 5}, "inc_id": null, "crew_status": null, "cluster": false, "etr": "2023-10-25T15:30:00Z", "etr_confidence": null, "comments": null, "cause": {"EN-US": "Pending crew assessment", "orig": "NOCAUSE"}, "crew_icon": false, "start_time": "2023-10-24T14:58Z", "lastFileUpdate": "2023-10-24T15:50:07.591Z"}, "geom": {"p": ["_~bdGfkyvN"]}, "source": "https://kubra.io/cluster-data/012/227de1f9-4adc-4fc9-98cb-dc2b847c0549/f94a9001-559d-46b5-9d94-e69fbdc030ee/public/cluster-1/030223210.json"},
{"id": "9-1", "title": "Area Outage", "desc": {"n_out": 1, "cust_a": {"val": 4, "mask": 5}, "inc_id": null, "crew_status": null, "cluster": false, "etr": "2023-10-24T20:30:00Z", "etr_confidence": null, "comments": null, "cause": {"EN-US": "Pending crew assessment", "orig": "NOCAUSE"}, "crew_icon": false, "start_time": "2023-10-24T13:42:15Z", "lastFileUpdate": "2023-10-24T15:50:07.591Z"}, "geom": {"p": ["k|rcGpjwxN"]}, "source": "https://kubra.io/cluster-data/012/227de1f9-4adc-4fc9-98cb-dc2b847c0549/f94a9001-559d-46b5-9d94-e69fbdc030ee/public/cluster-1/030223210.json"},
{"id": "9-2", "title": "Area Outage", "desc": {"n_out": 1, "cust_a": {"val": 94}, "inc_id": null, "crew_status": null, "cluster": false, "etr": "2023-10-24T18:30:00Z", "etr_confidence": null, "comments": null, "cause": {"EN-US": "Equipment problem", "orig": "EQUIPMENT FAILURE"}, "crew_icon": false, "start_time": "2023-10-24T06:27:32Z", "lastFileUpdate": "2023-10-24T15:50:07.591Z"}, "geom": {"a": ["mtgcGlkgyNE~ZwGVsMm]IeM@mC@i@dDYfF^dBXbB|AxC`DDrK"], "p": ["c_hcG`lgyN"]}, "source": "https://kubra.io/cluster-data/012/227de1f9-4adc-4fc9-98cb-dc2b847c0549/f94a9001-559d-46b5-9d94-e69fbdc030ee/public/cluster-1/030223210.json"},
{"id": "9-3", "title": "Area Outage", "desc": {"n_out": 1, "cust_a": {"val": 4, "mask": 5}, "inc_id": null, "crew_status": null, "cluster": false, "etr": "ETR-NULL", "etr_confidence": null, "comments": "Power problem is being assessed. A restoration estimate is in progress.", "cause": {"EN-US": "Pending crew assessment", "orig": "NOCAUSE"}, "crew_icon": false, "start_time": "2023-10-24T15:22:15Z", "lastFileUpdate": "2023-10-24T15:50:07.591Z"}, "geom": {"p": ["_y|bGduzxN"]}, "source": "https://kubra.io/cluster-data/012/227de1f9-4adc-4fc9-98cb-dc2b847c0549/f94a9001-559d-46b5-9d94-e69fbdc030ee/public/cluster-1/030223210.json"},
{"id": "9-4", "title": "Area Outage", "desc": {"n_out": 1, "cust_a": {"val": 4, "mask": 5}, "inc_id": null, "crew_status": null, "cluster": false, "etr": "2023-10-24T17:15:00Z", "etr_confidence": null, "comments": null, "cause": {"EN-US": "Equipment problem", "orig": "EQUIPMENT FAILURE"}, "crew_icon": false, "start_time": "2023-10-24T05:22:50Z", "lastFileUpdate": "2023-10-24T15:50:07.591Z"}, "geom": {"p": ["mgqeG~reyN"]}, "source": "https://kubra.io/cluster-data/012/227de1f9-4adc-4fc9-98cb-dc2b847c0549/f94a9001-559d-46b5-9d94-e69fbdc030ee/public/cluster-1/030223210.json"},
{"id": "9-5", "title": "Area Outage", "desc": {"n_out": 1, "cust_a": {"val": 4, "mask": 5}, "inc_id": null, "crew_status": null, "cluster": false, "etr": "2023-10-25T16:00:00Z", "etr_confidence": null, "comments": null, "cause": {"EN-US": "Reqd to repair/upgrade equip", "orig": "PLANNED INTENTIONAL"}, "crew_icon": false, "start_time": "2023-10-24T13:07:13.134Z", "lastFileUpdate": "2023-10-24T15:50:07.591Z"}, "geom": {"p": ["{godGzosxN"]}, "source": "https://kubra.io/cluster-data/012/227de1f9-4adc-4fc9-98cb-dc2b847c0549/f94a9001-559d-46b5-9d94-e69fbdc030ee/public/cluster-1/030223210.json"},
{"id": "12-0", "title": "Area Outage", "desc": {"n_out": 1, "cust_a": {"val": 4, "mask": 5}, "inc_id": null, "crew_status": null, "cluster": false, "etr": "2023-10-24T17:00:00Z", "etr_confidence": null, "comments": null, "cause": {"EN-US": "Pending crew assessment", "orig": "NOCAUSE"}, "crew_icon": false, "start_time": "2023-10-23T16:26:19Z", "lastFileUpdate": "2023-10-24T15:50:07.591Z"}, "geom": {"p": ["oc_bGvdjyN"]}, "source": "https://kubra.io/cluster-data/200/227de1f9-4adc-4fc9-98cb-dc2b847c0549/f94a9001-559d-46b5-9d94-e69fbdc030ee/public/cluster-1/030223212002.json"},
{"id": "12-1", "title": "Area Outage", "desc": {"n_out": 1, "cust_a": {"val": 4, "mask": 5}, "inc_id": null, "crew_status": null, "cluster": false, "etr": "2023-10-25T00:45:00Z", "etr_confidence": null, "comments": null, "cause": {"EN-US": "Pending crew assessment", "orig": "NOCAUSE"}, "crew_icon": false, "start_time": "2023-10-23T19:35:51Z", "lastFileUpdate": "2023-10-24T15:50:07.591Z"}, "geom": {"p": ["kqabGlsgyN"]}, "source": "https://kubra.io/cluster-data/200/227de1f9-4adc-4fc9-98cb-dc2b847c0549/f94a9001-559d-46b5-9d94-e69fbdc030ee/public/cluster-1/030223212002.json"},
{"id": "12-2", "title": "Area Outage", "desc": {"n_out": 1, "cust_a": {"val": 4, "mask": 5}, "inc_id": null, "crew_status": null, "cluster": false, "etr": "2023-10-25T14:45:00Z", "etr_confidence": null, "comments": null, "cause": {"EN-US": "Reqd to repair/upgrade equip", "orig": "PLANNED INTENTIONAL"}, "crew_icon": false, "start_time": "2023-10-24T14:13:13.326Z", "lastFileUpdate": "2023-10-24T15:50:07.591Z"}, "geom": {"p": ["{`cbG|`jyN"]}, "source": "https://kubra.io/cluster-data/200/227de1f9-4adc-4fc9-98cb-dc2b847c0549/f94a9001-559d-46b5-9d94-e69fbdc030ee/public/cluster-1/030223212002.json"},
{"id": "13-0", "title": "Area Outage", "desc": {"n_out": 1, "cust_a": {"val": 4, "mask": 5}, "inc_id": null, "crew_status": null, "cluster": false, "etr": "2023-10-24T17:00:00Z", "etr_confidence": null, "comments": null, "cause": {"EN-US": "Equipment problem", "orig": "EQUIPMENT FAILURE"}, "crew_icon": false, "start_time": "2023-10-23T15:44:57Z", "lastFileUpdate": "2023-10-24T15:50:07.591Z"}, "geom": {"p": ["eiwaGbggyN"]}, "source": "https://kubra.io/cluster-data/002/227de1f9-4adc-4fc9-98cb-dc2b847c0549/f94a9001-559d-46b5-9d94-e69fbdc030ee/public/cluster-1/0302232120200.json"},
{"id": "13-1", "title": "Area Outage", "desc": {"n_out": 1, "cust_a": {"val": 4, "mask": 5}, "inc_id": null, "crew_status": null, "cluster": false, "etr": "2023-10-24T18:45:00Z", "etr_confidence": null, "comments": null, "cause": {"EN-US": "Pending crew assessment", "orig": "NOCAUSE"}, "crew_icon": false, "start_time": "2023-10-23T12:50:05Z", "lastFileUpdate": "2023-10-24T15:50:07.591Z"}, "geom": {"p": ["uy{aGdudyN"]}, "source": "https://kubra.io/cluster-data/002/227de1f9-4adc-4fc9-98cb-dc2b847c0549/f94a9001-559d-46b5-9d94-e69fbdc030ee/public/cluster-1/0302232120200.json"},
{"id": "13-2", "title": "Area Outage", "desc": {"n_out": 1, "cust_a": {"val": 4, "mask": 5}, "inc_id": null, "crew_status": null, "cluster": false, "etr": "2023-10-25T12:30:00Z", "etr_confidence": null, "comments": null, "cause": {"EN-US": "Pending crew assessment", "orig": "NOCAUSE"}, "crew_icon": false, "start_time": "2023-10-24T09:38:50Z", "lastFileUpdate": "2023-10-24T15:50:07.591Z"}, "geom": {"p": ["sj{aGbocyN"]}, "source": "https://kubra.io/cluster-data/002/227de1f9-4adc-4fc9-98cb-dc2b847c0549/f94a9001-559d-46b5-9d94-e69fbdc030ee/public/cluster-1/0302232120200.json"}
]
